Workbook

Sheet 01_Резюме
A1: Исследование мобильного рынка (Google Play + App Store), 2026 — топ по выручке, топ по загрузкам, референсы под концепт
A2: Дата подготовки: 03.08.2026 · Все финансовые цифры — оценки сторонних аналитиков (Sensor Tower, AppMagic, Appfigures, mobilegamer.biz), а не отчётность издателей. Источники — на листе 06_Источники.
A4: 1. КЛЮЧЕВЫЕ ЦИФРЫ РЫНКА
A5: Показатель | B5: Значение | C5: Ед. изм. | D5: Комментарий / что это значит для нас | E5: Доля
A6: Прогноз выручки топ-100 мобильных игр, 2026 | B6: 53000 | C6: $ млн | D6: Рынок продолжает расти: почти вся выручка концентрируется в топ-100 — пробиться туда трудно, но потолок огромен.
A7: Выручка топ-100 мобильных игр, 2025 (факт) | B7: 46600 | C7: $ млн | D7: Рост год к году ≈ +14%.
A8: Доля топ-100 в общей выручке мобильных игр | B8: 0.58 | C8: % | D8: 42% выручки — за пределами топ-100: нишевый постапокалипсис может быть прибыльным без входа в топ-10.
A9: Жанр №1 по выручке 2026: RPG | B9: 24000 | C9: $ млн | D9: Самый ёмкий жанр, но и самый дорогой по производству. | E9: =B9/$B$15
A10: Жанр №2: Strategy (4X / выживание) | B10: 19000 | C10: $ млн | D10: ЦЕЛЕВОЙ жанр: сюда попадают Whiteout Survival, Kingshot, State of Survival — база + ресурсы + альянсы. | E10: =B10/$B$15
A11: Жанр №3: Casual | B11: 16000 | C11: $ млн | D11: Источник дешёвого трафика; гибридные механики оттуда стоит заимствовать. | E11: =B11/$B$15
A12: Рост выручки hybrid-casual сегмента, 2025→2026 | B12: 0.37 | C12: % | D12: Самый быстрорастущий сегмент: простое ядро + глубокая мета + IAP.
A13: Рост выручки от подписок в играх, г/г | B13: 0.28 | C13: % | D13: Подписка (батл-пасс + VIP) — обязательный слой монетизации для нашей игры.
A14: Доля топ-игр, использующих 5–7 механик монетизации | B14: 0.83 | C14: % | D14: Одной валюты мало: нужны пасс, стартовые наборы, VIP, ускорители, косметика.
A15: Сумма топ-3 жанров (RPG + Strategy + Casual) | B15: =SUM(B9:B11) | C15: $ млн | D15: Доля каждого жанра считается от этой суммы (колонка «Доля»).
A17: 2. ГЛАВНЫЕ ВЫВОДЫ ПОД ВАШ КОНЦЕПТ
A18: 1. Деньги в 2026-м делает «выживание + строительство базы» | B18: 4 из топ-10 по выручке — survival/4X: Whiteout Survival (~$110 млн/мес), Kingshot ($812 млн за первый год), Last War, плюс State of Survival ($1,69 млрд lifetime). Ваш сеттинг попадает точно в самый денежный тренд.
A19: 2. Но топ-грос игры — не 2D и не про движение персонажа | B19: Они изометрические/3D, управление — тапы по карте города. Ваше «движение по X/Y» — это другая ниша (Last Day on Earth, Survivor.io, Dysmantle). Значит: монетизацию берём у 4X, геймплей — у top-down выживачей.
A20: 3. Ближайший коммерческий аналог по геймплею — Last Day on Earth: Survival (Kefir) | B20: Top-down, движение стиком по X/Y, крафт, база, грядки, вылазки за ресурсы, F2P с премиум-валютой. Это самый близкий к вашему ТЗ успешный F2P-проект.
A21: 4. Ферма + автоматизация в 2D продаются, но в основном как premium | B21: Stardew Valley, Forager, Core Keeper, Terraria — это платные игры. F2P-исключения: Deep Town (автоматизация + идл, F2P) и Harvest Town (ферма, F2P). Значит автоматизацию надо монетизировать через ускорители/слоты, а не через продажу игры.
A22: 5. Мирный город-хаб — недооценённая, но проверенная механика | B22: В Terraria город NPC = торговля + квесты, в LifeAfter — город Осень. Для F2P это ещё и точка входа в социалку (кланы, торговля между игроками) и в монетизацию (слоты торговли, VIP-скидки).
A23: 6. Монетизация: freemium с 5–7 механиками | B23: 83% топ-игр комбинируют 5–7 механик. Минимальный набор для вас: премиум-валюта, батл-пасс (сезоны), стартовый набор, VIP/подписка, ускорители производства, слоты автоматизации, косметика для базы.
A24: 7. Загрузки ≠ выручка | B24: Лидеры загрузок — Roblox, Free Fire, Block Blast, Subway Surfers. Это гипер/казуал. В нише выживания объём загрузок ниже, но ARPU в 5–15 раз выше — ориентируйтесь на выручку, а не на скачивания.
A25: 8. Оптимальная стратегия | B25: «Last Day on Earth» по управлению + «Forager/Stardew» по ферме и автоматизации + «Whiteout Survival» по монетизации и live-ops + мирный хаб-город как социальное ядро.
A27: 3. КАК ЧИТАТЬ ФАЙЛ
A28: 02_Топ_выручка | B28: Топ-10 мобильных игр мира по выручке в 2026 (H1) — бенчмарк монетизации.
A29: 03_Топ_загрузки | B29: Лидеры по скачиваниям 2026 — бенчмарк по трафику и удержанию.
A30: 04_Референсы | B30: 22 игры, релевантные вашему ТЗ: перспектива, графика, монетизация, цифры, что забрать.
A31: 05_Скоринг | B31: Оценка каждой игры 0–10 по 7 вашим критериям + вес критерия + итоговый приоритет и ранг.
A32: 06_Источники | B32: Ссылки на все использованные данные.
A34: Синим цветом отмечены исходные числа (данные аналитиков), чёрным — рассчитанные формулами.

Sheet 02_Топ_выручка
A1: Топ-10 мобильных игр мира по выручке, 2026 (первое полугодие)
A2: Оценки net-выручки сторов (без учёта 30% комиссии, рекламы и китайского Android-рынка). Источники: mobilegamer.biz / Sensor Tower / AppMagic / Appfigures.
A3: № | B3: Игра | C3: Издатель | D3: Жанр | E3: Модель монетизации | F3: Выручка, $ млн/мес (оценка) | G3: Lifetime / накопленная выручка | H3: Период и комментарий | I3: Релевантность концепту (1–5) | J3: Что забрать себе
A4: 1 | B4: Honor of Kings | C4: Tencent | D4: MOBA | E4: F2P: скины, герои, пропуск | F4: 160 | G4: > $2,5 млрд за 2026 | H4: Пик $194 млн (январь 2026); 98% выручки — Китай | I4: 1 | J4: Косметика как основной драйвер: продавать не силу, а вид базы/персонажа
A5: 2 | B5: Whiteout Survival | C5: Century Games | D5: 4X-выживание (ледниковый апокалипсис) | E5: F2P: валюта, наборы, VIP, пропуск | F5: 110 | G5: > $3 млрд за 2,5 года | H5: Лидер по выручке в июне 2026; ~2 млн DAU | I5: 5 | J5: ЭТАЛОН: постапокалипсис + город + ресурсы + альянсы. Копировать структуру экономики и live-ops
A6: 3 | B6: Last War: Survival | C6: First Fun (FunFly) | D6: 4X + гибридные мини-игры | E6: F2P: валюта, наборы, пропуск | F6: 71 | G6: Ранее $120–135 млн/мес (2025) | H6: Июнь 2026 — $71 млн, снижение | I6: 4 | J6: Гибридная воронка: казуальная мини-игра в рекламе → мидкорная мета внутри
A7: 4 | B7: Royal Match | C7: Dream Games | D7: Puzzle (match-3) | E7: F2P: жизни, ходы, ивенты | F7: 100 | G7: н/д | H7: Стабильно ~$100 млн/мес, №2 в июне 2026 | I7: 2 | J7: Календарь ивентов и «мягкие» стены прогресса
A8: 5 | B8: PUBG Mobile | C8: Tencent / Krafton | D8: Battle Royale | E8: F2P: пропуск, косметика | F8: 133 | G8: н/д | H8: Пик $133 млн (февраль 2026), волатилен | I8: 1 | J8: Сезонность и коллаборации с IP
A9: 6 | B9: Gossip Harbor | C9: Microfun | D9: Merge + сюжет | E9: F2P: энергия, наборы | F9: 100 | G9: н/д | H9: Растёт, №4 по выручке в июне 2026 | I9: 2 | J9: Сюжетная нарезка как удержание в казуальной обёртке
A10: 7 | B10: Roblox | C10: Roblox Corp. | D10: UGC-платформа | E10: F2P: Robux | G10: н/д | H10: Снижение г/г по сравнению с H1 2025; №1 по загрузкам | I10: 2 | J10: UGC и социальность как бесконечный контент
A11: 8 | B11: MONOPOLY GO! | C11: Scopely | D11: Board / social casino-like | E11: F2P: кубики, наборы | F11: 85 | G11: н/д | H11: ~$85 млн/мес IAP, №5 по выручке в июне 2026 | I11: 2 | J11: Соревновательные ивенты с наградами по лигам
A12: 9 | B12: Candy Crush Saga | C12: King (Microsoft) | D12: Puzzle | E12: F2P: ходы, бустеры | F12: 95 | G12: > $20 млрд lifetime (за 13 лет) | H12: ~$95 млн/мес IAP | I12: 1 | J12: Долгожительство за счёт бесконечного контента уровней
A13: 10 | B13: Kingshot | C13: Century Games | D13: 4X-выживание + tower defense + idle | E13: F2P: валюта, наборы, VIP | F13: 93 | G13: $811,9 млн за первые 12 месяцев | H13: Пик $102,2 млн (январь 2026); 42 млн загрузок | I13: 5 | J13: Смешение жанров: idle + защита базы + 4X. Быстрый вход, глубокая мета
B14: Среднее по топ-10 (где есть данные) | F14: =AVERAGE(F4:F13) | H14: Средняя релевантность топ-10 нашему концепту → | I14: =AVERAGE(I4:I13)
B16: Игр с релевантностью 4–5 в топ-10: | F16: =COUNTIF(I4:I13,">=4") | H16: Все они — survival/постапокалипсис с базой. Это подтверждает выбор сеттинга.

Sheet 03_Топ_загрузки
A1: Лидеры по скачиваниям, 2026 (Google Play + App Store)
A2: Данные Sensor Tower / AppMagic / Udonis. Загрузки показывают силу трафика, а не доходность — сверяйте с листом 02.
A3: № | B3: Игра | C3: Издатель | D3: Жанр | E3: Показатель загрузок | F3: Позиция / период | G3: Релевантность концепту (1–5) | H3: Вывод для нас
A4: 1 | B4: ROBLOX | C4: Roblox Corp. | D4: UGC-платформа | E4: №1 в мире по загрузкам (июнь 2026) | F4: Обогнал Free Fire в июне 2026 | G4: 2 | H4: Дети и подростки — крупнейший пул трафика; UGC = бесконечное удержание
A5: 2 | B5: Free Fire | C5: Garena / Sea | D5: Battle Royale | E5: №1 в Google Play (годовой зачёт) | F5: №2 в мире по загрузкам, июнь 2026 | G5: 1 | H5: Оптимизация под слабые устройства = рынки SEA, LATAM, Индия
A6: 3 | B6: Block Blast! | C6: Hungry Studio | D6: Puzzle | E6: 89 млн загрузок в App Store за год; №1 в App Store 2 года подряд | F6: №1 в мире по загрузкам (январь 2026) | G6: 1 | H6: Максимально простая механика + агрессивный UA
A7: 4 | B7: Subway Surfers | C7: SYBO / Kiloo | D7: Endless runner | E7: > 2 млрд загрузок за всё время | F7: Бессменный лидер по накопленным загрузкам | G7: 3 | H7: Движение по X/Y + постоянные апдейты мира = вечная жизнь проекта
A8: 5 | B8: Heartopia | C8: NetEase | D8: Life-sim / avatar | E8: Лидер по приросту загрузок в мире | F8: Сильнее всего — США и Юго-Восточная Азия | G8: 3 | H8: Уютный сеттинг и социальность сейчас на подъёме — контраст к жёсткому постапоку
A9: 6 | B9: Kingshot | C9: Century Games | D9: 4X-выживание | E9: 42 млн загрузок за ~12 месяцев | F9: Обгоняет Whiteout Survival по загрузкам на 56% (февраль 2026) | G9: 5 | H9: Показывает, что survival-4X можно масштабировать по трафику, а не только по ARPU
A10: 7 | B10: Survivor.io | C10: Habby | D10: 2D top-down roguelite | E10: > 80 млн установок (к середине 2025) | F10: На старте: 37 млн загрузок и $75 млн за 2 месяца | G10: 4 | H10: ЭТАЛОН вирусности для 2D top-down: простое управление одним пальцем + TikTok-креативы
A11: 8 | B11: Last Day on Earth: Survival | C11: Kefir | D11: Top-down выживание-крафт | E11: Десятки млн установок (точные данные закрыты) | F11: Многолетний лидер ниши зомби-выживания | G11: 5 | H11: Ближайший аналог по геймплею; проверенная воронка UA в нише
B12: Средняя релевантность лидеров загрузок | G12: =AVERAGE(G4:G11)

Sheet 04_Референсы
A1: Референсы под ваш концепт: 2D, движение по X/Y, freemium, постапокалипсис, ферма + автоматизация + мирный город
A2: 22 игры, сгруппированные по категориям A–F. Финансовые данные — оценки аналитиков; «н/д» означает, что публичных данных нет.
A3: № | B3: Игра | C3: Разработчик / издатель | D3: Категория | E3: Перспектива и управление | F3: Графика | G3: Монетизация | H3: Выручка (оценка) | I3: Загрузки (оценка) | J3: Ключевые механики | K3: Что забрать в свою игру | L3: Риск / ограничение
A4: 1 | B4: Whiteout Survival | C4: Century Games | D4: A. Топ-грос 4X-выживание | E4: Изометрия, тап по карте | F4: 3D-стилизованная | G4: F2P: премиум-валюта, наборы, VIP, пропуск | H4: ~$110 млн/мес; > $3 млрд lifetime | I4: Десятки млн MAU, ~2 млн DAU | J4: Постройка города, обогрев, ресурсы, герои, альянсы, PvP, сезоны | K4: Структура экономики и live-ops: ежедневные ивенты, сезоны, альянсовые цели | L4: Нет 2D и нет прямого управления персонажем
A5: 2 | B5: Kingshot | C5: Century Games | D5: A. Топ-грос 4X-выживание | E5: Изометрия + tower defense | F5: 3D-стилизованная | G5: F2P: валюта, наборы, VIP | H5: $811,9 млн за 12 месяцев; пик $102,2 млн/мес | I5: 42 млн загрузок за год | J5: Idle + защита базы + 4X-мета | K5: Гибрид: быстрая экшн-петля на входе, 4X-мета на удержании | L5: Сеттинг средневековый, не постапокалипсис
A6: 3 | B6: Last War: Survival | C6: First Fun (FunFly) | D6: A. Топ-грос 4X-выживание | E6: Изометрия | F6: 3D | G6: F2P: валюта, наборы, пропуск | H6: $71 млн/мес (июнь 2026) | I6: Сотни млн установок | J6: Мини-игра «ворота» + 4X-база + зомби-сеттинг | K6: Механика UA: casual-крючок в креативах ведёт в мидкор | L6: Падение выручки — жанр перегрет
A7: 4 | B7: State of Survival | C7: FunPlus / KingsGroup | D7: A. Топ-грос 4X-выживание | E7: Изометрия | F7: 3D-стилизованная | G7: F2P: валюта, наборы, пропуск | H7: $1,69 млрд lifetime; $63 млн за 2025 | I7: Сотни млн установок | J7: Зомби-постапокалипсис, поселение, герои, альянсы, коллаборации (The Walking Dead) | K7: IP-коллаборации как инструмент возврата аудитории | L7: Проект прошёл пик
A8: 5 | B8: Doomsday: Last Survivors | C8: IGG | D8: A. Топ-грос 4X-выживание | E8: Изометрия | F8: 3D | G8: F2P: валюта, наборы | H8: HK$1,14 млрд за год; рекорд HK$130 млн/мес | I8: н/д | J8: Постапокалипсис, база, союзы, PvP | K8: Доказательство, что постапок-4X растёт даже в 2026 (+12% г/г) | L8: Высокая конкуренция
A9: 6 | B9: LifeAfter | C9: NetEase | D9: B. F2P выживание-крафт | E9: 3D от третьего лица | F9: 3D | G9: F2P: валюта, наборы, косметика | H9: $125 млн+ (97% — Китай) | I9: Десятки млн | J9: Выживание, крафт, дом, ГОРОД-ХАБ «Осень», торговля, задания | K9: ЭТАЛОН мирного города-хаба: торговля игроков + миссии + социальные точки | L9: 3D-графика и высокий бюджет
A10: 7 | B10: Last Day on Earth: Survival | C10: Kefir | D10: B. F2P выживание-крафт | E10: Top-down, стик — движение по X/Y | F10: 2.5D, стилизованная | G10: F2P: премиум-валюта, ускорители, наборы, пропуск | H10: н/д (оценка: десятки млн $ в год) | I10: Десятки млн установок | J10: Вылазки по локациям, крафт, база, грядки, транспорт, рейды | K10: ГЛАВНЫЙ РЕФЕРЕНС: управление, петля «вылазка → база → апгрейд», монетизация ускорителей | L10: Устаревший UX, жёсткий гринд
A11: 8 | B11: Grim Soul: Dark Survival RPG | C11: Brickworks Games | D11: B. F2P выживание-крафт | E11: Top-down, стик | F11: 2.5D тёмное фэнтези | G11: F2P: валюта, наборы, подписка | H11: Небольшая, но стабильная (нишевая) | I11: 10 млн+ установок | J11: Тот же каркас, что LDoE, но в тёмном фэнтези | K11: Пример успешного «реskin» проверенного каркаса под другой сеттинг | L11: Небольшой масштаб выручки
A12: 9 | B12: Dawn of Zombies: Survival | C12: Royal Ark | D12: B. F2P выживание-крафт | E12: Top-down, стик | F12: 2.5D постапокалипсис | G12: F2P: валюта, наборы, подписка | H12: Нишевая | I12: 10 млн+ (≈14 млн) установок | J12: Постъядерный мир, радиация, фракции, NPC-квесты, база, фермерство | K12: Фракции и NPC-квесты как источник контента вне гринда | L12: Слабая ретенция, много багов по отзывам
A13: 10 | B13: Days After: Zombie Survival | C13: Alternativa Games | D13: B. F2P выживание-крафт | E13: Top-down, стик | F13: 2.5D | G13: F2P: валюта, наборы | H13: Нишевая | I13: 10 млн+ (≈18 млн) установок | J13: Выживание, крафт, база, зомби | K13: Подтверждение спроса: даже средние игры ниши берут 10+ млн установок | L13: Клон-рынок, сложно выделиться
A14: 11 | B14: Fallout Shelter | C14: Bethesda | D14: F. 2D-строительство базы | E14: 2D вид сбоку, «разрез» убежища | F14: 2D мультяшная, очень чистая | G14: F2P: ланчбоксы (лутбоксы), без рекламы | H14: > $90 млн lifetime | I14: 100 млн+ загрузок | J14: Строительство комнат, распределение жителей, производство, вылазки в пустошь | K14: ЭТАЛОН 2D-подачи постапокалипсиса и мягкой монетизации без давления | L14: Нет прямого управления персонажем по X/Y
A15: 12 | B15: Sheltered 2 | C15: Unicube / Team17 | D15: F. 2D-строительство базы | E15: 2D вид сбоку, бункер | F15: 2D пиксель-арт | G15: Premium (разовая покупка) | H15: Нишевая (PC/консоли) | I15: Сотни тысяч | J15: Бункер, ресурсы, мораль, вылазки, крафт | K15: Атмосфера и менеджмент выживших; дизайн UI бункера | L15: Premium-модель не подходит под ваше ТЗ
... A25: 22 | B25: Survivor.io | C25: Habby | D25: E. 2D-экшн F2P | E25: Top-down, управление одним пальцем по X/Y | F25: 2D, яркая и чистая | G25: F2P: валюта, снаряжение, пропуск, подписка | H25: $476 млн lifetime (≈40% выручки Habby) | I25: 80 млн+ установок | J25: Зомби-апокалипсис, автобой, прокачка снаряжения, сезоны | K25: ЭТАЛОН управления и «сочности» 2D-боя + вирусные креативы (TikTok) | L25: Нет строительства, фермы и хаба

Sheet 05_Скоринг
A1: Скоринг референсов по вашим критериям (0–10) с весами
A2: Названия игр и категории подтягиваются формулами с листа 04_Референсы (зелёный шрифт). Веса в жёлтых ячейках можно менять — итоговые оценки и ранги пересчитаются автоматически. | Q2: Веса итоговой оценки (можно менять)
Q3: Вес соответствия концепту | R3: 0.6
C4: Вес критерия, % → | D4: 15 | E4: 15 | F4: 20 | G4: 15 | H4: 10 | I4: 15 | J4: 10 | K4: =SUM(D4:J4) | L4: ← сумма весов, должна быть 100 | Q4: Вес коммерческого успеха | R4: 0.4
A5: № | B5: Игра | C5: Категория | D5: Движение персонажа по X/Y | E5: Качество 2D-графики | F5: Freemium: премиум-предметы и валюта | G5: Постапокалиптический сеттинг | H5: Фермерство / выращивание растений | I5: Строительство + автоматизация | J5: Мирный город-хаб: обмен и миссии | K5: Соответствие концепту (0–10) | L5: Коммерческий успех (0–10) | M5: ИТОГОВЫЙ ПРИОРИТЕТ (0–10) | N5: Ранг | O5: Роль референса | Q5: Сумма весов (должна быть 100%) | R5: =R3+R4
A6: 1 | B6: ='04_Референсы'!B4 | C6: ='04_Референсы'!D4 | D6: 3 | E6: 5 | F6: 10 | G6: 8 | H6: 6 | I6: 9 | J6: 8 | K6: =SUMPRODUCT($D6:$J6,$D$4:$J$4)/SUM($D$4:$J$4) | L6: 10 | M6: =$R$3*K6+$R$4*L6 | N6: =RANK(M6,$M$6:$M$27,0) | O6: Бенчмарк монетизации и live-ops
A7: 2 | B7: ='04_Референсы'!B5 | C7: ='04_Референсы'!D5 | D7: 3 | E7: 5 | F7: 10 | G7: 5 | H7: 6 | I7: 9 | J7: 8 | K7: =SUMPRODUCT($D7:$J7,$D$4:$J$4)/SUM($D$4:$J$4) | L7: 10 | M7: =$R$3*K7+$R$4*L7 | N7: =RANK(M7,$M$6:$M$27,0) | O7: Бенчмарк гибридного онбординга
A8: 3 | B8: ='04_Референсы'!B6 | C8: ='04_Референсы'!D6 | D8: 4 | E8: 4 | F8: 10 | G8: 7 | H8: 3 | I8: 8 | J8: 7 | K8: =SUMPRODUCT($D8:$J8,$D$4:$J$4)/SUM($D$4:$J$4) | L8: 10 | M8: =$R$3*K8+$R$4*L8 | N8: =RANK(M8,$M$6:$M$27,0) | O8: Бенчмарк UA-воронки
A9: 4 | B9: ='04_Референсы'!B7 | C9: ='04_Референсы'!D7 | D9: 3 | E9: 5 | F9: 10 | G9: 9 | H9: 5 | I9: 8 | J9: 8 | K9: =SUMPRODUCT($D9:$J9,$D$4:$J$4)/SUM($D$4:$J$4) | L9: 9 | M9: =$R$3*K9+$R$4*L9 | N9: =RANK(M9,$M$6:$M$27,0) | O9: Бенчмарк постапок-меты и IP-коллабораций
A10: 5 | B10: ='04_Референсы'!B8 | C10: ='04_Референсы'!D8 | D10: 3 | E10: 4 | F10: 10 | G10: 9 | H10: 5 | I10: 8 | J10: 8 | K10: =SUMPRODUCT($D10:$J10,$D$4:$J$4)/SUM($D$4:$J$4) | L10: 8 | M10: =$R$3*K10+$R$4*L10 | N10: =RANK(M10,$M$6:$M$27,0) | O10: Подтверждение спроса на постапокалипсис
A11: 6 | B11: ='04_Референсы'!B9 | C11: ='04_Референсы'!D9 | D11: 2 | E11: 2 | F11: 10 | G11: 10 | H11: 6 | I11: 8 | J11: 9 | K11: =SUMPRODUCT($D11:$J11,$D$4:$J$4)/SUM($D$4:$J$4) | L11: 8 | M11: =$R$3*K11+$R$4*L11 | N11: =RANK(M11,$M$6:$M$27,0) | O11: Референс мирного города-хаба
A12: 7 | B12: ='04_Референсы'!B10 | C12: ='04_Референсы'!D10 | D12: 9 | E12: 7 | F12: 10 | G12: 10 | H12: 7 | I12: 7 | J12: 6 | K12: =SUMPRODUCT($D12:$J12,$D$4:$J$4)/SUM($D$4:$J$4) | L12: 8 | M12: =$R$3*K12+$R$4*L12 | N12: =RANK(M12,$M$6:$M$27,0) | O12: ГЛАВНЫЙ референс: геймплей + монетизация
A13: 8 | B13: ='04_Референсы'!B11 | C13: ='04_Референсы'!D11 | D13: 9 | E13: 7 | F13: 10 | G13: 6 | H13: 6 | I13: 7 | J13: 5 | K13: =SUMPRODUCT($D13:$J13,$D$4:$J$4)/SUM($D$4:$J$4) | L13: 6 | M13: =$R$3*K13+$R$4*L13 | N13: =RANK(M13,$M$6:$M$27,0) | O13: Референс переноса каркаса в новый сеттинг
A14: 9 | B14: ='04_Референсы'!B12 | C14: ='04_Референсы'!D12 | D14: 9 | E14: 7 | F14: 10 | G14: 10 | H14: 7 | I14: 7 | J14: 8 | K14: =SUMPRODUCT($D14:$J14,$D$4:$J$4)/SUM($D$4:$J$4) | L14: 5 | M14: =$R$3*K14+$R$4*L14 | N14: =RANK(M14,$M$6:$M$27,0) | O14: Референс фракций и NPC-квестов
A15: 10 | B15: ='04_Референсы'!B13 | C15: ='04_Референсы'!D13 | D15: 9 | E15: 7 | F15: 10 | G15: 10 | H15: 6 | I15: 7 | J15: 6 | K15: =SUMPRODUCT($D15:$J15,$D$4:$J$4)/SUM($D$4:$J$4) | L15: 4 | M15: =$R$3*K15+$R$4*L15 | N15: =RANK(M15,$M$6:$M$27,0) | O15: Ориентир по нижней планке качества ниши
A16: 11 | B16: ='04_Референсы'!B14 | C16: ='04_Референсы'!D14 | D16: 4 | E16: 9 | F16: 9 | G16: 10 | H16: 4 | I16: 8 | J16: 5 | K16: =SUMPRODUCT($D16:$J16,$D$4:$J$4)/SUM($D$4:$J$4) | L16: 6 | M16: =$R$3*K16+$R$4*L16 | N16: =RANK(M16,$M$6:$M$27,0) | O16: Референс 2D-подачи и мягкой монетизации
A17: 12 | B17: ='04_Референсы'!B15 | C17: ='04_Референсы'!D15 | D17: 6 | E17: 8 | F17: 2 | G17: 10 | H17: 5 | I17: 7 | J17: 4 | K17: =SUMPRODUCT($D17:$J17,$D$4:$J$4)/SUM($D$4:$J$4) | L17: 2 | M17: =$R$3*K17+$R$4*L17 | N17: =RANK(M17,$M$6:$M$27,0) | O17: Референс атмосферы и менеджмента выживших
... A27: 22 | B27: ='04_Референсы'!B25 | C27: ='04_Референсы'!D25 | D27: 9 | E27: 8 | F27: 10 | G27: 7 | H27: 0 | I27: 1 | J27: 3 | K27: =SUMPRODUCT($D27:$J27,$D$4:$J$4)/SUM($D$4:$J$4) | L27: 8 | M27: =$R$3*K27+$R$4*L27 | N27: =RANK(M27,$M$6:$M$27,0) | O27: ГЛАВНЫЙ референс управления и вирусности
B29: СВОДКА ПО КАТЕГОРИЯМ
B30: Категория | C30: Кол-во игр | D30: Средн. соответствие | E30: Средн. приоритет | F30: Максимум приоритета
B31: A. Топ-грос 4X-выживание | C31: =COUNTIF($C$6:$C$27,$B31) | D31: =IFERROR(AVERAGEIF($C$6:$C$27,$B31,$K$6:$K$27),"") | E31: =IFERROR(AVERAGEIF($C$6:$C$27,$B31,$M$6:$M$27),"") | F31: =SUMPRODUCT(MAX(($C$6:$C$27=$B31)*$M$6:$M$27))
B32: B. F2P выживание-крафт | C32: =COUNTIF($C$6:$C$27,$B32) | D32: =IFERROR(AVERAGEIF($C$6:$C$27,$B32,$K$6:$K$27),"") | E32: =IFERROR(AVERAGEIF($C$6:$C$27,$B32,$M$6:$M$27),"") | F32: =SUMPRODUCT(MAX(($C$6:$C$27=$B32)*$M$6:$M$27))
B33: F. 2D-строительство базы | C33: =COUNTIF($C$6:$C$27,$B33) | D33: =IFERROR(AVERAGEIF($C$6:$C$27,$B33,$K$6:$K$27),"") | E33: =IFERROR(AVERAGEIF($C$6:$C$27,$B33,$M$6:$M$27),"") | F33: =SUMPRODUCT(MAX(($C$6:$C$27=$B33)*$M$6:$M$27))
B34: C. 2D премиум выживание | C34: =COUNTIF($C$6:$C$27,$B34) | D34: =IFERROR(AVERAGEIF($C$6:$C$27,$B34,$K$6:$K$27),"") | E34: =IFERROR(AVERAGEIF($C$6:$C$27,$B34,$M$6:$M$27),"") | F34: =SUMPRODUCT(MAX(($C$6:$C$27=$B34)*$M$6:$M$27))
B35: D. 2D автоматизация | C35: =COUNTIF($C$6:$C$27,$B35) | D35: =IFERROR(AVERAGEIF($C$6:$C$27,$B35,$K$6:$K$27),"") | E35: =IFERROR(AVERAGEIF($C$6:$C$27,$B35,$M$6:$M$27),"") | F35: =SUMPRODUCT(MAX(($C$6:$C$27=$B35)*$M$6:$M$27))
B36: E. 2D-экшн F2P | C36: =COUNTIF($C$6:$C$27,$B36) | D36: =IFERROR(AVERAGEIF($C$6:$C$27,$B36,$K$6:$K$27),"") | E36: =IFERROR(AVERAGEIF($C$6:$C$27,$B36,$M$6:$M$27),"") | F36: =SUMPRODUCT(MAX(($C$6:$C$27=$B36)*$M$6:$M$27))
B38: Как считается: «Соответствие концепту» = взвешенная сумма 7 критериев / сумма весов (веса — жёлтая строка 4). «Итоговый приоритет» = 60% соответствия + 40% коммерческого успеха (веса — жёлтые ячейки R3:R4).
B39: Оценки 0–10 выставлены экспертно по механике игр (синий шрифт — исходные значения, их можно править). Коммерческий успех оценён по данным листов 02–04.

Sheet 06_Источники
A1: Источники данных
A2: Все ссылки проверены 03.08.2026. Данные по выручке — оценки аналитических компаний, официальную отчётность издатели не раскрывают.
A3: № | B3: Что взято | C3: Источник | D3: Ссылка
A4: 1 | B4: Топ-10 игр мира по выручке 2026 (H1), помесячные оценки | C4: mobilegamer.biz | D4: https://mobilegamer.biz/2026s-top-10-grossing-mobile-games-so-far-honor-of-kings-whiteout-survival-lastwar-royal-match-pubg-mobile-more/
A5: 2 | B5: Топ-10 по выручке и загрузкам, июнь 2026 | C5: Sensor Tower | D5: https://sensortower.com/blog/top-10-worldwide-mobile-games-by-revenue-and-downloads-in-june-2026
A6: 3 | B6: Топ-10 по выручке и загрузкам, январь 2026 | C6: Sensor Tower | D6: https://sensortower.com/blog/top-10-worldwide-mobile-games-by-revenue-and-downloads-in-january-2026
A7: 4 | B7: Прогноз $53 млрд для топ-100 игр в 2026 | C7: Sensor Tower / Digital Today | D7: https://www.digitaltoday.co.kr/en/view/55387/sensortower-top-100-mobile-games-forecast-53-billion-dollars-revenue-this-year
A8: 5 | B8: Whiteout Survival: $3 млрд за 2,5 года | C8: PocketGamer.biz | D8: https://www.pocketgamer.biz/whiteout-survival-hits-3bn-in-player-spending-in-under-25-years/
A9: 6 | B9: Whiteout Survival: статистика выручки и аудитории | C9: Udonis | D9: https://www.blog.udonis.co/statistics/whiteout-survival
A10: 7 | B10: Kingshot: $500 млн за 11 месяцев, $811,9 млн за 12 месяцев, 42 млн загрузок | C10: Appfigures | D10: https://appfigures.com/resources/insights/kingshot-500m-revenue-century-games
A11: 8 | B11: Kingshot обгоняет Whiteout Survival по загрузкам | C11: mobilegamer.biz | D11: https://mobilegamer.biz/data-digest-kingshot-outpaces-whiteout-survival-female-players-overlooked-casual-market-flat-januarys-top-titles-more/
A12: 9 | B12: State of Survival: $1,69 млрд lifetime, $63 млн за 2025 | C12: Udonis | D12: https://www.blog.udonis.co/statistics/state-of-survival
A13: 10 | B13: Doomsday: Last Survivors — рекорд HK$130 млн/мес, HK$1,14 млрд за год | C13: IGG / TradingView News | D13: https://www.tradingview.com/news/reuters.com,2026-03-25:newsml_ACN105845:0-igg-doomsday-last-survivors-achieves-record-high-monthly-gross-billing-of-hk-130-million/
A14: 11 | B14: LifeAfter: $125 млн выручки, 97% — Китай | C14: Sensor Tower | D14: https://sensortower.com/blog/lifeafter-revenue
A15: 12 | B15: Survivor.io: $476 млн lifetime, доля в выручке Habby | C15: mobilegamer.biz | D15: https://mobilegamer.biz/data-digest-savvys-moonton-swoop-liftoff-kills-ipo-habby-hits-2bn-fallout-shelter-more/
... A27: 24 | B27: Обзор 2D пиксельных выживалок 2026 (Terraria, Core Keeper, Project Zomboid mobile) | C27: Beatcop / Mobi.gg | D27: https://mobi.gg/en/tops/top-17-best-survival-games-mobile-android-ios/
